{
  "maa-run": {
    "x86_64-unknown-linux-gnu": {
      "version": "0.2.4",
      "tag": "maa_run-v0.2.4",
      "name": "maa_run-v0.2.4-x86_64-unknown-linux-gnu.tar.gz",
      "size": 1819923,
      "sha256sum": "c3d9a5c8326d6bd569dc8553dd9190143457685fe68695b59035ef6322dd48d9"
    },
    "universal-apple-darwin": {
      "version": "0.2.4",
      "tag": "maa_run-v0.2.4",
      "name": "maa_run-v0.2.4-universal-apple-darwin.zip",
      "size": 1800053,
      "sha256sum": "50aea8e211a04dbd71c56c772cba0722c63bff1529457fd3252119209b20cdf8"
    }
  },
  "maa-cli": {
    "x86_64-unknown-linux-gnu": {
      "version": "0.2.3",
      "tag": "maa_cli-v0.2.3",
      "name": "maa_cli-v0.2.3-x86_64-unknown-linux-gnu.tar.gz",
      "size": 3135845,
      "sha256sum": "9a743b3c63bcfdff41789fc0a00be0ec0aa92fe265e3841bb5d7223bac3deb4e"
    },
    "universal-apple-darwin": {
      "version": "0.2.2",
      "tag": "maa_cli-v0.2.2",
      "name": "maa_cli-v0.2.2-universal-apple-darwin.zip",
      "size": 4076810,
      "sha256sum": "959baf42fceb6873ac7b7b11f5d70eea4d9c50883e195ad749112d84ce42e015"
    }
  }
}
